[
  {
    "description": "You have gained 10 reputation!!",
    "min": 0,
    "max": 1,
    "action": {
      "type": "reputation",
      "amount": 10
    }
  },
  {
    "description": "You have gained 5 reputation!",
    "min": 1,
    "max": 2.5,
    "action": {
      "type": "reputation",
      "amount": 5
    }
  },
  {
    "description": "You have gained 3 reputation!",
    "min": 2.5,
    "max": 9.5,
    "action": {
      "type": "reputation",
      "amount": 3
    }
  },
  {
    "description": "You have lost 7 reputation!!",
    "min": 9.5,
    "max": 13.5,
    "action": {
      "type": "reputation",
      "amount": -7
    }
  },
  {
    "description": "You have lost 5 reputation!",
    "min": 13.5,
    "max": 20,
    "action": {
      "type": "reputation",
      "amount": -5
    }
  },
  {
    "description": "You have gained 500 score!",
    "min": 20,
    "max": 45,
    "action": {
      "type": "score",
      "amount": 500
    }
  },
  {
    "description": "You have lost 2000 score!",
    "min": 45,
    "max": 60,
    "action": {
      "type": "score",
      "amount": -2000
    }
  },
  {
    "description": "You have gained 2500 score!",
    "min": 60,
    "max": 70,
    "action": {
      "type": "score",
      "amount": 2500
    }
  },
  {
    "description": "You have gained 10000 score!!",
    "min": 70,
    "max": 75,
    "action": {
      "type": "score",
      "amount": 10000
    }
  },
  {
    "description": "You have gained 5 tokens!",
    "min": 75,
    "max": 80,
    "action": {
      "type": "token",
      "amount": 5
    }
  },
  {
    "description": "You can change the server icon! <@135410033524604928>",
    "min": 80,
    "max": 80.5,
    "action": {
      "type": "",
      "amount": 0
    }
  },
  {
    "description": "You didn't get anything...",
    "min": 80.5,
    "max": 101,
    "action": {
      "type": "",
      "amount": 0
    }
  }
]
